README.md
pyproject.toml
setup.py
./fortran/es.f90
./fortran/fcoll_grid.f90
./fortran/ionization_map.f90
./fortran/matter_fields.f90
./fortran/matter_fields_haloes.f90
./fortran/nrint.f90
./fortran/onedspline.f90
./fortran/pc.f90
./fortran/powspec.f90
./fortran/rsd.f90
./fortran/sort_grid_points.f90
reion_script.egg-info/PKG-INFO
reion_script.egg-info/SOURCES.txt
reion_script.egg-info/dependency_links.txt
reion_script.egg-info/requires.txt
reion_script.egg-info/top_level.txt
script/__init__.py
script/script.py
script/two_lpt.py
script/utils.py