Metadata-Version: 2.1
Name: reion_script
Version: 1.0.9
Summary: A semi-numerical code for reionization with explicit photon conservation
Author-Email: Tirthankar Roy Choudhury <tirth@ncra.tifr.res.in>
Project-URL: Homepage, https://bitbucket.org/rctirthankar/script/src/master/script/
Requires-Python: >=3.6
Requires-Dist: numpy==1.24.4
